serialize_gpio/__init__.py
serialize_gpio/controller.py
serialize_gpio/exceptions.py
serialize_gpio/inspection.py
serialize_gpio/messageManipulators.py
serialize_gpio-0.1.0.dist-info/METADATA
serialize_gpio-0.1.0.dist-info/RECORD
serialize_gpio-0.1.0.dist-info/WHEEL
serialize_gpio-0.1.0.dist-info/top_level.txt
