Metadata-Version: 2.1
Name: serialize-gpio
Version: 0.1.0
Summary: Python library for controlling Raspberry Pi® GPIO Pins through a serializable message protocol.
Home-page: https://github.com/PabloPaglilla/serialize_gpio
Author: Pablo Paglilla
Author-email: pablopaglilla16@gmail.com
License: UNKNOWN
Platform: UNKNOWN
Classifier: Programming Language :: Python :: 3
Classifier: License :: OSI Approved :: MIT License
Classifier: Operating System :: POSIX :: Linux
Classifier: Intended Audience :: Developers
Classifier: Intended Audience :: Education
